[
  {
    "folderName": "Three_Harem_Girls by 0741374b194cbd7db8f8",
    "characterName": "Three_Harem_Girls",
    "characterName_Sanitized": "Three_Harem_Girls",
    "fileId": "1496f632a17003a4118e993836473919.gz",
    "link": "https://perchance.org/ai-character-chat?data=Three_Harem_Girls~1496f632a17003a4118e993836473919.gz",
    "shareLinkFileHash": "3c2235b86ec7fc0b7aef87b2f705f49ed0d3d2e3c656d5646a3ff92f618b9396",
    "authorName": "0741374b194cbd7db8f8",
    "authorId": "0741374b194cbd7db8f8"
  }
]