{
  "folderName": "ai-character-chat+chat",
  "message": "https://perchance.org/ai-character-chat?data=Chara_(smoltale_V2)~177c69f91cb8ac54748c75813b5e01fb.gz",
  "messageId": "67a82ed83400e30ae25a66a3",
  "publicId": "dea561134fabda7abea9",
  "selfDeclaredHistorialPublicIds": [],
  "time": 1739075288009,
  "userNickname": "SANSLOVESKETCHUPVERYVERYVERYMUCH LOVEFORKETCHUP",
  "userAvatarUrl": "https://user-uploads.perchance.org/file/7f1bc7b62b1a31be5e77ba68c65ba96f.jpg",
  "username": "fanon",
  "replyingTo": "67a82eb93400e30ae25a666f"
}