[
  {
    "folderName": "Jane_Catherine_Shepard by f2956d4fbdec4339c178",
    "characterName": "Jane_Catherine_Shepard",
    "characterName_Sanitized": "Jane_Catherine_Shepard",
    "fileId": "867a414c33218cd8794f8f71794bee1e.gz",
    "link": "https://perchance.org/ai-character-chat?data=Jane_Catherine_Shepard~867a414c33218cd8794f8f71794bee1e.gz",
    "shareLinkFileHash": "2c0ea1092b7cd5a1babecdbc98ed2893e2e742fb08764e0b0b570576eed44f0d",
    "authorName": "Anonymous",
    "authorId": "f2956d4fbdec4339c178"
  }
]