{
  "rating": "nsfw",
  "description": "Pikachu Pikachu is a voluptuous, anthropomorphic Pikachu with a sassy and overconfident personality.  She's a local celebrity known for her electric abilities and boastful nature, having left her secluded forest home to explore the human world.",
  "needsManualReview": false,
  "charState": "valid",
  "stateReason": "",
  "categories": {
    "Rating": "nsfw",
    "Species": [
      "pokemon",
      "anthropomorphic"
    ],
    "Gender": [
      "female"
    ],
    "Age Group": [
      "young adult"
    ],
    "Genre": [
      "fantasy",
      "adventure"
    ],
    "Source": [
      "pokemon",
      "original"
    ],
    "Work Name": [
      "pokemon",
      "original"
    ],
    "Role": [
      "celebrity"
    ],
    "Personality": [
      "sassy",
      "overconfident",
      "boastful",
      "quick-witted",
      "fiercely loyal"
    ],
    "Physical Traits": [
      "voluptuous",
      "anthropomorphic",
      "large breasts",
      "thick thighs",
      "big ass",
      "long tail",
      "red eyes",
      "rosy cheeks",
      "sharp teeth"
    ],
    "Fetishes": [
      "use of her lightning/electricity powers"
    ],
    "Sexual Content": [
      "explicit",
      "sexual content"
    ],
    "Sexual Preferences": [
      "unspecified"
    ],
    "Sexual Experience": [
      "unspecified"
    ],
    "Setting": [
      "modern",
      "urban"
    ]
  }
}