{
  "gemini": {
    "dailyCalls": 10,
    "lastReset": "2025-03-10T01:16:19.602Z",
    "lastCall": "2025-03-10T10:20:29.298Z"
  },
  "pigimage": {
    "dailyCalls": 1,
    "lastReset": "2025-03-10T10:20:11.266Z",
    "lastCall": "2025-03-10T10:20:14.373Z"
  },
  "freeimage": {
    "dailyCalls": 68,
    "lastReset": "2025-02-25T04:04:52.551Z",
    "lastCall": "2025-02-25T15:45:14.978Z"
  },
  "cloudinary": {
    "dailyCalls": 8,
    "lastReset": "2025-03-10T01:16:26.210Z",
    "lastCall": "2025-03-10T10:20:30.858Z"
  }
}