{
  "chat": {
    "messageId": "682ad076ca830f5677697240",
    "time": 1747636342692,
    "messagesAnalyzed_Total": 783363,
    "messagesAnalyzed_lastRun": 915,
    "charactersFound_Total": 669,
    "charactersFound_lastRun": 0,
    "charactersIgnored_Total": 1,
    "charactersIgnored_lastRun": 0,
    "duplicatedCharacterLink_Total": 0,
    "duplicatedCharacterLink_lastRun": 0,
    "duplicatedCharacterHash_Total": 0,
    "duplicatedCharacterHash_lastRun": 0,
    "deltaMinutes": 194
  },
  "chill": {
    "messageId": "682aafd6ca830f5677693b75",
    "time": 1747627990018,
    "messagesAnalyzed_Total": 34406,
    "messagesAnalyzed_lastRun": 2,
    "charactersFound_Total": 108,
    "charactersFound_lastRun": 0,
    "charactersIgnored_Total": 0,
    "charactersIgnored_lastRun": 0,
    "duplicatedCharacterLink_Total": 0,
    "duplicatedCharacterLink_lastRun": 0,
    "duplicatedCharacterHash_Total": 0,
    "duplicatedCharacterHash_lastRun": 0,
    "deltaMinutes": 190
  },
  "rp": {
    "messageId": "682ac57bca830f567769622b",
    "time": 1747633531045,
    "messagesAnalyzed_Total": 219049,
    "messagesAnalyzed_lastRun": 404,
    "charactersFound_Total": 42,
    "charactersFound_lastRun": 0,
    "charactersIgnored_Total": 0,
    "charactersIgnored_lastRun": 0,
    "duplicatedCharacterLink_Total": 0,
    "duplicatedCharacterLink_lastRun": 0,
    "duplicatedCharacterHash_Total": 0,
    "duplicatedCharacterHash_lastRun": 0,
    "deltaMinutes": 147
  },
  "spam": {
    "messageId": "682a754eca830f567768ca2a",
    "time": 1747613006960,
    "messagesAnalyzed_Total": 18672,
    "messagesAnalyzed_lastRun": 0,
    "charactersFound_Total": 741,
    "charactersFound_lastRun": 0,
    "charactersIgnored_Total": 0,
    "charactersIgnored_lastRun": 0,
    "duplicatedCharacterLink_Total": 0,
    "duplicatedCharacterLink_lastRun": 0,
    "duplicatedCharacterHash_Total": 0,
    "duplicatedCharacterHash_lastRun": 0,
    "deltaMinutes": 0
  },
  "vent": {
    "messageId": "682acb95ca830f5677696b6e",
    "time": 1747635093449,
    "messagesAnalyzed_Total": 47319,
    "messagesAnalyzed_lastRun": 17,
    "charactersFound_Total": 16,
    "charactersFound_lastRun": 0,
    "charactersIgnored_Total": 0,
    "charactersIgnored_lastRun": 0,
    "duplicatedCharacterLink_Total": 0,
    "duplicatedCharacterLink_lastRun": 0,
    "duplicatedCharacterHash_Total": 0,
    "duplicatedCharacterHash_lastRun": 0,
    "deltaMinutes": 685
  },
  "share": {
    "messageId": "682accccca830f5677696d15",
    "time": 1747635404335,
    "messagesAnalyzed_Total": 13513,
    "messagesAnalyzed_lastRun": 24,
    "charactersFound_Total": 2819,
    "charactersFound_lastRun": 1,
    "charactersIgnored_Total": 11,
    "charactersIgnored_lastRun": 0,
    "duplicatedCharacterLink_Total": 0,
    "duplicatedCharacterLink_lastRun": 0,
    "duplicatedCharacterHash_Total": 0,
    "duplicatedCharacterHash_lastRun": 0,
    "deltaMinutes": 600
  },
  "botshare": {
    "messageId": "682ac206ca830f5677695be1",
    "time": 1747632646547,
    "messagesAnalyzed_Total": 1946,
    "messagesAnalyzed_lastRun": 1,
    "charactersFound_Total": 470,
    "charactersFound_lastRun": 0,
    "charactersIgnored_Total": 0,
    "charactersIgnored_lastRun": 0,
    "duplicatedCharacterLink_Total": 0,
    "duplicatedCharacterLink_lastRun": 0,
    "duplicatedCharacterHash_Total": 0,
    "duplicatedCharacterHash_lastRun": 0,
    "deltaMinutes": 1113
  },
  "makeabot": {
    "messageId": "6816534380c839f98a01dcd8",
    "time": 1746293571127,
    "messagesAnalyzed_Total": 121,
    "messagesAnalyzed_lastRun": 0,
    "charactersFound_Total": 18,
    "charactersFound_lastRun": 0,
    "charactersIgnored_Total": 0,
    "charactersIgnored_lastRun": 0,
    "duplicatedCharacterLink_Total": 0,
    "duplicatedCharacterLink_lastRun": 0,
    "duplicatedCharacterHash_Total": 0,
    "duplicatedCharacterHash_lastRun": 0,
    "deltaMinutes": 0
  },
  "nsfw": {
    "messageId": "682ac1adca830f5677695b34",
    "time": 1747632557329,
    "messagesAnalyzed_Total": 5231,
    "messagesAnalyzed_lastRun": 5,
    "charactersFound_Total": 427,
    "charactersFound_lastRun": 2,
    "charactersIgnored_Total": 0,
    "charactersIgnored_lastRun": 0,
    "duplicatedCharacterLink_Total": 0,
    "duplicatedCharacterLink_lastRun": 0,
    "duplicatedCharacterHash_Total": 0,
    "duplicatedCharacterHash_lastRun": 0,
    "deltaMinutes": 1057
  },
  "channel-hub": {
    "messageId": "682975c0ca830f56776764c4",
    "time": 1747547584383,
    "messagesAnalyzed_Total": 959,
    "messagesAnalyzed_lastRun": 0,
    "charactersFound_Total": 8,
    "charactersFound_lastRun": 0,
    "charactersIgnored_Total": 0,
    "charactersIgnored_lastRun": 0,
    "duplicatedCharacterLink_Total": 0,
    "duplicatedCharacterLink_lastRun": 0,
    "duplicatedCharacterHash_Total": 0,
    "duplicatedCharacterHash_lastRun": 0,
    "deltaMinutes": 0
  }
}