{
  "chat": {
    "messageId": "68d9b3fd00d9d1f9fd991a67",
    "time": 1759097853120,
    "messagesAnalyzed_Total": 1905084,
    "messagesAnalyzed_lastRun": 1159,
    "charactersFound_Total": 5503,
    "charactersFound_lastRun": 0,
    "charactersIgnored_Total": 2,
    "charactersIgnored_lastRun": 0,
    "duplicatedCharacterLink_Total": 0,
    "duplicatedCharacterLink_lastRun": 0,
    "duplicatedCharacterHash_Total": 0,
    "duplicatedCharacterHash_lastRun": 0,
    "deltaMinutes": 117
  },
  "chill": {
    "messageId": "68d9ac1600d9d1f9fd99077b",
    "time": 1759095830720,
    "messagesAnalyzed_Total": 75315,
    "messagesAnalyzed_lastRun": 19,
    "charactersFound_Total": 119,
    "charactersFound_lastRun": 0,
    "charactersIgnored_Total": 0,
    "charactersIgnored_lastRun": 0,
    "duplicatedCharacterLink_Total": 0,
    "duplicatedCharacterLink_lastRun": 0,
    "duplicatedCharacterHash_Total": 0,
    "duplicatedCharacterHash_lastRun": 0,
    "deltaMinutes": 106
  },
  "rp": {
    "messageId": "68d9b31700d9d1f9fd991887",
    "time": 1759097623737,
    "messagesAnalyzed_Total": 463176,
    "messagesAnalyzed_lastRun": 4,
    "charactersFound_Total": 56,
    "charactersFound_lastRun": 0,
    "charactersIgnored_Total": 0,
    "charactersIgnored_lastRun": 0,
    "duplicatedCharacterLink_Total": 0,
    "duplicatedCharacterLink_lastRun": 0,
    "duplicatedCharacterHash_Total": 0,
    "duplicatedCharacterHash_lastRun": 0,
    "deltaMinutes": 142
  },
  "spam": {
    "messageId": "68d9a59800d9d1f9fd98f71c",
    "time": 1759094168722,
    "messagesAnalyzed_Total": 21909,
    "messagesAnalyzed_lastRun": 2,
    "charactersFound_Total": 771,
    "charactersFound_lastRun": 0,
    "charactersIgnored_Total": 0,
    "charactersIgnored_lastRun": 0,
    "duplicatedCharacterLink_Total": 0,
    "duplicatedCharacterLink_lastRun": 0,
    "duplicatedCharacterHash_Total": 0,
    "duplicatedCharacterHash_lastRun": 0,
    "deltaMinutes": 280
  },
  "vent": {
    "messageId": "68d991f400d9d1f9fd98c2d4",
    "time": 1759089140360,
    "messagesAnalyzed_Total": 65206,
    "messagesAnalyzed_lastRun": 0,
    "charactersFound_Total": 18,
    "charactersFound_lastRun": 0,
    "charactersIgnored_Total": 0,
    "charactersIgnored_lastRun": 0,
    "duplicatedCharacterLink_Total": 0,
    "duplicatedCharacterLink_lastRun": 0,
    "duplicatedCharacterHash_Total": 0,
    "duplicatedCharacterHash_lastRun": 0,
    "deltaMinutes": 0
  },
  "share": {
    "messageId": "68d992be00d9d1f9fd98c4ce",
    "time": 1759089342056,
    "messagesAnalyzed_Total": 21369,
    "messagesAnalyzed_lastRun": 0,
    "charactersFound_Total": 3477,
    "charactersFound_lastRun": 0,
    "charactersIgnored_Total": 32,
    "charactersIgnored_lastRun": 0,
    "duplicatedCharacterLink_Total": 0,
    "duplicatedCharacterLink_lastRun": 0,
    "duplicatedCharacterHash_Total": 0,
    "duplicatedCharacterHash_lastRun": 0,
    "deltaMinutes": 0
  },
  "botshare": {
    "messageId": "68d97ff900d9d1f9fd98943f",
    "time": 1759084537252,
    "messagesAnalyzed_Total": 2084,
    "messagesAnalyzed_lastRun": 0,
    "charactersFound_Total": 507,
    "charactersFound_lastRun": 0,
    "charactersIgnored_Total": 0,
    "charactersIgnored_lastRun": 0,
    "duplicatedCharacterLink_Total": 0,
    "duplicatedCharacterLink_lastRun": 0,
    "duplicatedCharacterHash_Total": 0,
    "duplicatedCharacterHash_lastRun": 0,
    "deltaMinutes": 35
  },
  "makeabot": {
    "messageId": "686eb9b177661ecb7ae23e82",
    "time": 1752086961055,
    "messagesAnalyzed_Total": 129,
    "messagesAnalyzed_lastRun": 0,
    "charactersFound_Total": 18,
    "charactersFound_lastRun": 0,
    "charactersIgnored_Total": 0,
    "charactersIgnored_lastRun": 0,
    "duplicatedCharacterLink_Total": 0,
    "duplicatedCharacterLink_lastRun": 0,
    "duplicatedCharacterHash_Total": 0,
    "duplicatedCharacterHash_lastRun": 0,
    "deltaMinutes": 0
  },
  "nsfw": {
    "messageId": "68d9791800d9d1f9fd98828b",
    "time": 1759082776482,
    "messagesAnalyzed_Total": 8468,
    "messagesAnalyzed_lastRun": 0,
    "charactersFound_Total": 739,
    "charactersFound_lastRun": 0,
    "charactersIgnored_Total": 1,
    "charactersIgnored_lastRun": 0,
    "duplicatedCharacterLink_Total": 0,
    "duplicatedCharacterLink_lastRun": 0,
    "duplicatedCharacterHash_Total": 0,
    "duplicatedCharacterHash_lastRun": 0,
    "deltaMinutes": 0
  },
  "channel-hub": {
    "messageId": "68d9384900d9d1f9fd97fe4c",
    "time": 1759066185362,
    "messagesAnalyzed_Total": 1129,
    "messagesAnalyzed_lastRun": 0,
    "charactersFound_Total": 10,
    "charactersFound_lastRun": 0,
    "charactersIgnored_Total": 0,
    "charactersIgnored_lastRun": 0,
    "duplicatedCharacterLink_Total": 0,
    "duplicatedCharacterLink_lastRun": 0,
    "duplicatedCharacterHash_Total": 0,
    "duplicatedCharacterHash_lastRun": 0,
    "deltaMinutes": 0
  }
}