{
  "chat": {
    "messageId": "68e5d350772a817973207911",
    "time": 1759892304992,
    "messagesAnalyzed_Total": 2006162,
    "messagesAnalyzed_lastRun": 594,
    "charactersFound_Total": 5559,
    "charactersFound_lastRun": 0,
    "charactersIgnored_Total": 2,
    "charactersIgnored_lastRun": 0,
    "duplicatedCharacterLink_Total": 0,
    "duplicatedCharacterLink_lastRun": 0,
    "duplicatedCharacterHash_Total": 0,
    "duplicatedCharacterHash_lastRun": 0,
    "deltaMinutes": 81
  },
  "chill": {
    "messageId": "68e5c41b772a817973204e31",
    "time": 1759888411655,
    "messagesAnalyzed_Total": 75835,
    "messagesAnalyzed_lastRun": 21,
    "charactersFound_Total": 121,
    "charactersFound_lastRun": 0,
    "charactersIgnored_Total": 0,
    "charactersIgnored_lastRun": 0,
    "duplicatedCharacterLink_Total": 0,
    "duplicatedCharacterLink_lastRun": 0,
    "duplicatedCharacterHash_Total": 0,
    "duplicatedCharacterHash_lastRun": 0,
    "deltaMinutes": 49
  },
  "rp": {
    "messageId": "68e5d331772a8179732078bb",
    "time": 1759892273570,
    "messagesAnalyzed_Total": 469230,
    "messagesAnalyzed_lastRun": 183,
    "charactersFound_Total": 58,
    "charactersFound_lastRun": 0,
    "charactersIgnored_Total": 0,
    "charactersIgnored_lastRun": 0,
    "duplicatedCharacterLink_Total": 0,
    "duplicatedCharacterLink_lastRun": 0,
    "duplicatedCharacterHash_Total": 0,
    "duplicatedCharacterHash_lastRun": 0,
    "deltaMinutes": 94
  },
  "spam": {
    "messageId": "68e5c880772a817973205a54",
    "time": 1759889536898,
    "messagesAnalyzed_Total": 22107,
    "messagesAnalyzed_lastRun": 5,
    "charactersFound_Total": 776,
    "charactersFound_lastRun": 0,
    "charactersIgnored_Total": 0,
    "charactersIgnored_lastRun": 0,
    "duplicatedCharacterLink_Total": 0,
    "duplicatedCharacterLink_lastRun": 0,
    "duplicatedCharacterHash_Total": 0,
    "duplicatedCharacterHash_lastRun": 0,
    "deltaMinutes": 182
  },
  "vent": {
    "messageId": "68e5b988772a81797320301b",
    "time": 1759885704032,
    "messagesAnalyzed_Total": 67618,
    "messagesAnalyzed_lastRun": 0,
    "charactersFound_Total": 18,
    "charactersFound_lastRun": 0,
    "charactersIgnored_Total": 0,
    "charactersIgnored_lastRun": 0,
    "duplicatedCharacterLink_Total": 0,
    "duplicatedCharacterLink_lastRun": 0,
    "duplicatedCharacterHash_Total": 0,
    "duplicatedCharacterHash_lastRun": 0,
    "deltaMinutes": 170
  },
  "share": {
    "messageId": "68e5b895772a817973202d1c",
    "time": 1759885461179,
    "messagesAnalyzed_Total": 21675,
    "messagesAnalyzed_lastRun": 0,
    "charactersFound_Total": 3497,
    "charactersFound_lastRun": 0,
    "charactersIgnored_Total": 32,
    "charactersIgnored_lastRun": 0,
    "duplicatedCharacterLink_Total": 0,
    "duplicatedCharacterLink_lastRun": 0,
    "duplicatedCharacterHash_Total": 0,
    "duplicatedCharacterHash_lastRun": 0,
    "deltaMinutes": 169
  },
  "botshare": {
    "messageId": "68e3c1ae772a8179731b090b",
    "time": 1759756718127,
    "messagesAnalyzed_Total": 2092,
    "messagesAnalyzed_lastRun": 0,
    "charactersFound_Total": 508,
    "charactersFound_lastRun": 0,
    "charactersIgnored_Total": 0,
    "charactersIgnored_lastRun": 0,
    "duplicatedCharacterLink_Total": 0,
    "duplicatedCharacterLink_lastRun": 0,
    "duplicatedCharacterHash_Total": 0,
    "duplicatedCharacterHash_lastRun": 0,
    "deltaMinutes": 0
  },
  "makeabot": {
    "messageId": "686eb9b177661ecb7ae23e82",
    "time": 1752086961055,
    "messagesAnalyzed_Total": 129,
    "messagesAnalyzed_lastRun": 0,
    "charactersFound_Total": 18,
    "charactersFound_lastRun": 0,
    "charactersIgnored_Total": 0,
    "charactersIgnored_lastRun": 0,
    "duplicatedCharacterLink_Total": 0,
    "duplicatedCharacterLink_lastRun": 0,
    "duplicatedCharacterHash_Total": 0,
    "duplicatedCharacterHash_lastRun": 0,
    "deltaMinutes": 0
  },
  "nsfw": {
    "messageId": "68e5b86c772a817973202ca3",
    "time": 1759885420688,
    "messagesAnalyzed_Total": 8657,
    "messagesAnalyzed_lastRun": 0,
    "charactersFound_Total": 739,
    "charactersFound_lastRun": 0,
    "charactersIgnored_Total": 1,
    "charactersIgnored_lastRun": 0,
    "duplicatedCharacterLink_Total": 0,
    "duplicatedCharacterLink_lastRun": 0,
    "duplicatedCharacterHash_Total": 0,
    "duplicatedCharacterHash_lastRun": 0,
    "deltaMinutes": 176
  },
  "channel-hub": {
    "messageId": "68ded85b772a8179730fe53c",
    "time": 1759434843410,
    "messagesAnalyzed_Total": 1131,
    "messagesAnalyzed_lastRun": 0,
    "charactersFound_Total": 10,
    "charactersFound_lastRun": 0,
    "charactersIgnored_Total": 0,
    "charactersIgnored_lastRun": 0,
    "duplicatedCharacterLink_Total": 0,
    "duplicatedCharacterLink_lastRun": 0,
    "duplicatedCharacterHash_Total": 0,
    "duplicatedCharacterHash_lastRun": 0,
    "deltaMinutes": 0
  }
}