{
  "chat": {
    "messageId": "67c9cc69a115bd48114485c5",
    "time": 1741278313737,
    "messagesAnalyzed_Total": 197346,
    "messagesAnalyzed_lastRun": 200,
    "charactersFound_Total": 157,
    "charactersFound_lastRun": 1,
    "charactersIgnored_Total": 1,
    "charactersIgnored_lastRun": 0,
    "duplicatedCharacterLink_Total": 0,
    "duplicatedCharacterLink_lastRun": 0,
    "duplicatedCharacterHash_Total": 0,
    "duplicatedCharacterHash_lastRun": 0,
    "deltaMinutes": 127
  },
  "chill": {
    "messageId": "67c92641a115bd481143c565",
    "time": 1741235777129,
    "messagesAnalyzed_Total": 5728,
    "messagesAnalyzed_lastRun": 0,
    "charactersFound_Total": 68,
    "charactersFound_lastRun": 0,
    "charactersIgnored_Total": 0,
    "charactersIgnored_lastRun": 0,
    "duplicatedCharacterLink_Total": 0,
    "duplicatedCharacterLink_lastRun": 0,
    "duplicatedCharacterHash_Total": 0,
    "duplicatedCharacterHash_lastRun": 0,
    "deltaMinutes": 0
  },
  "rp": {
    "messageId": "67c9cc6ca115bd48114485cc",
    "time": 1741278316520,
    "messagesAnalyzed_Total": 43524,
    "messagesAnalyzed_lastRun": 200,
    "charactersFound_Total": 16,
    "charactersFound_lastRun": 1,
    "charactersIgnored_Total": 0,
    "charactersIgnored_lastRun": 0,
    "duplicatedCharacterLink_Total": 0,
    "duplicatedCharacterLink_lastRun": 0,
    "duplicatedCharacterHash_Total": 0,
    "duplicatedCharacterHash_lastRun": 0,
    "deltaMinutes": 127
  },
  "spam": {
    "messageId": "67c9a538a115bd48114441f0",
    "time": 1741268280918,
    "messagesAnalyzed_Total": 6738,
    "messagesAnalyzed_lastRun": 0,
    "charactersFound_Total": 230,
    "charactersFound_lastRun": 0,
    "charactersIgnored_Total": 0,
    "charactersIgnored_lastRun": 0,
    "duplicatedCharacterLink_Total": 0,
    "duplicatedCharacterLink_lastRun": 0,
    "duplicatedCharacterHash_Total": 0,
    "duplicatedCharacterHash_lastRun": 0,
    "deltaMinutes": 91
  },
  "vent": {
    "messageId": "67c984cea115bd48114422a6",
    "time": 1741259982708,
    "messagesAnalyzed_Total": 17244,
    "messagesAnalyzed_lastRun": 0,
    "charactersFound_Total": 9,
    "charactersFound_lastRun": 0,
    "charactersIgnored_Total": 0,
    "charactersIgnored_lastRun": 0,
    "duplicatedCharacterLink_Total": 0,
    "duplicatedCharacterLink_lastRun": 0,
    "duplicatedCharacterHash_Total": 0,
    "duplicatedCharacterHash_lastRun": 0,
    "deltaMinutes": 0
  },
  "share": {
    "messageId": "67c9a6b1a115bd4811444440",
    "time": 1741268657435,
    "messagesAnalyzed_Total": 7294,
    "messagesAnalyzed_lastRun": 0,
    "charactersFound_Total": 1348,
    "charactersFound_lastRun": 0,
    "charactersIgnored_Total": 7,
    "charactersIgnored_lastRun": 0,
    "duplicatedCharacterLink_Total": 0,
    "duplicatedCharacterLink_lastRun": 0,
    "duplicatedCharacterHash_Total": 0,
    "duplicatedCharacterHash_lastRun": 0,
    "deltaMinutes": 70
  }
}