{
  "chat": {
    "messageId": "681f286eca830f567757d37b",
    "time": 1746872430426,
    "messagesAnalyzed_Total": 707065,
    "messagesAnalyzed_lastRun": 238,
    "charactersFound_Total": 517,
    "charactersFound_lastRun": 0,
    "charactersIgnored_Total": 1,
    "charactersIgnored_lastRun": 0,
    "duplicatedCharacterLink_Total": 0,
    "duplicatedCharacterLink_lastRun": 0,
    "duplicatedCharacterHash_Total": 0,
    "duplicatedCharacterHash_lastRun": 0,
    "deltaMinutes": 117
  },
  "chill": {
    "messageId": "681ee877ca830f5677579ce2",
    "time": 1746856055219,
    "messagesAnalyzed_Total": 24953,
    "messagesAnalyzed_lastRun": 0,
    "charactersFound_Total": 108,
    "charactersFound_lastRun": 0,
    "charactersIgnored_Total": 0,
    "charactersIgnored_lastRun": 0,
    "duplicatedCharacterLink_Total": 0,
    "duplicatedCharacterLink_lastRun": 0,
    "duplicatedCharacterHash_Total": 0,
    "duplicatedCharacterHash_lastRun": 0,
    "deltaMinutes": 0
  },
  "rp": {
    "messageId": "681f1b41ca830f567757cb01",
    "time": 1746869057522,
    "messagesAnalyzed_Total": 190952,
    "messagesAnalyzed_lastRun": 1,
    "charactersFound_Total": 36,
    "charactersFound_lastRun": 0,
    "charactersIgnored_Total": 0,
    "charactersIgnored_lastRun": 0,
    "duplicatedCharacterLink_Total": 0,
    "duplicatedCharacterLink_lastRun": 0,
    "duplicatedCharacterHash_Total": 0,
    "duplicatedCharacterHash_lastRun": 0,
    "deltaMinutes": 255
  },
  "spam": {
    "messageId": "681f1bceca830f567757cb45",
    "time": 1746869198641,
    "messagesAnalyzed_Total": 18492,
    "messagesAnalyzed_lastRun": 1,
    "charactersFound_Total": 740,
    "charactersFound_lastRun": 0,
    "charactersIgnored_Total": 0,
    "charactersIgnored_lastRun": 0,
    "duplicatedCharacterLink_Total": 0,
    "duplicatedCharacterLink_lastRun": 0,
    "duplicatedCharacterHash_Total": 0,
    "duplicatedCharacterHash_lastRun": 0,
    "deltaMinutes": 70
  },
  "vent": {
    "messageId": "681f06d5ca830f567757bb16",
    "time": 1746863829278,
    "messagesAnalyzed_Total": 45465,
    "messagesAnalyzed_lastRun": 0,
    "charactersFound_Total": 16,
    "charactersFound_lastRun": 0,
    "charactersIgnored_Total": 0,
    "charactersIgnored_lastRun": 0,
    "duplicatedCharacterLink_Total": 0,
    "duplicatedCharacterLink_lastRun": 0,
    "duplicatedCharacterHash_Total": 0,
    "duplicatedCharacterHash_lastRun": 0,
    "deltaMinutes": 379
  },
  "share": {
    "messageId": "681f0734ca830f567757bb65",
    "time": 1746863924305,
    "messagesAnalyzed_Total": 12814,
    "messagesAnalyzed_lastRun": 0,
    "charactersFound_Total": 2764,
    "charactersFound_lastRun": 0,
    "charactersIgnored_Total": 10,
    "charactersIgnored_lastRun": 0,
    "duplicatedCharacterLink_Total": 0,
    "duplicatedCharacterLink_lastRun": 0,
    "duplicatedCharacterHash_Total": 0,
    "duplicatedCharacterHash_lastRun": 0,
    "deltaMinutes": 431
  },
  "botshare": {
    "messageId": "681eb7a8ca830f5677574ae4",
    "time": 1746843560605,
    "messagesAnalyzed_Total": 1935,
    "messagesAnalyzed_lastRun": 0,
    "charactersFound_Total": 469,
    "charactersFound_lastRun": 0,
    "charactersIgnored_Total": 0,
    "charactersIgnored_lastRun": 0,
    "duplicatedCharacterLink_Total": 0,
    "duplicatedCharacterLink_lastRun": 0,
    "duplicatedCharacterHash_Total": 0,
    "duplicatedCharacterHash_lastRun": 0,
    "deltaMinutes": 3746
  },
  "makeabot": {
    "messageId": "6816534380c839f98a01dcd8",
    "time": 1746293571127,
    "messagesAnalyzed_Total": 121,
    "messagesAnalyzed_lastRun": 0,
    "charactersFound_Total": 18,
    "charactersFound_lastRun": 0,
    "charactersIgnored_Total": 0,
    "charactersIgnored_lastRun": 0,
    "duplicatedCharacterLink_Total": 0,
    "duplicatedCharacterLink_lastRun": 0,
    "duplicatedCharacterHash_Total": 0,
    "duplicatedCharacterHash_lastRun": 0,
    "deltaMinutes": 0
  },
  "nsfw": {
    "messageId": "681eaa88ca830f5677573524",
    "time": 1746840200668,
    "messagesAnalyzed_Total": 5053,
    "messagesAnalyzed_lastRun": 0,
    "charactersFound_Total": 356,
    "charactersFound_lastRun": 0,
    "charactersIgnored_Total": 0,
    "charactersIgnored_lastRun": 0,
    "duplicatedCharacterLink_Total": 0,
    "duplicatedCharacterLink_lastRun": 0,
    "duplicatedCharacterHash_Total": 0,
    "duplicatedCharacterHash_lastRun": 0,
    "deltaMinutes": 377
  },
  "channel-hub": {
    "messageId": "681c0d7e80c839f98a0ad444",
    "time": 1746668926597,
    "messagesAnalyzed_Total": 948,
    "messagesAnalyzed_lastRun": 0,
    "charactersFound_Total": 8,
    "charactersFound_lastRun": 0,
    "charactersIgnored_Total": 0,
    "charactersIgnored_lastRun": 0,
    "duplicatedCharacterLink_Total": 0,
    "duplicatedCharacterLink_lastRun": 0,
    "duplicatedCharacterHash_Total": 0,
    "duplicatedCharacterHash_lastRun": 0,
    "deltaMinutes": 0
  }
}