{
  "chat": {
    "messageId": "67b1530912cdd8e6110be79e",
    "time": 1739674377018,
    "messagesAnalyzed_Total": 105216,
    "messagesAnalyzed_lastRun": 581,
    "charactersFound_Total": 109,
    "charactersFound_lastRun": 1,
    "charactersIgnored_Total": 1,
    "charactersIgnored_lastRun": 0,
    "deltaMinutes": 75
  },
  "chill": {
    "messageId": "67b0b5b512cdd8e6110ae4de",
    "time": 1739634101950,
    "messagesAnalyzed_Total": 5092,
    "messagesAnalyzed_lastRun": 0,
    "charactersFound_Total": 68,
    "charactersFound_lastRun": 0,
    "charactersIgnored_Total": 0,
    "charactersIgnored_lastRun": 0,
    "deltaMinutes": 0
  },
  "rp": {
    "messageId": "67b14b2612cdd8e6110bd6c5",
    "time": 1739672358494,
    "messagesAnalyzed_Total": 19074,
    "messagesAnalyzed_lastRun": 95,
    "charactersFound_Total": 2,
    "charactersFound_lastRun": 0,
    "charactersIgnored_Total": 0,
    "charactersIgnored_lastRun": 0,
    "deltaMinutes": 41
  },
  "spam": {
    "messageId": "67b10da812cdd8e6110b6c97",
    "time": 1739656616468,
    "messagesAnalyzed_Total": 6238,
    "messagesAnalyzed_lastRun": 0,
    "charactersFound_Total": 221,
    "charactersFound_lastRun": 0,
    "charactersIgnored_Total": 0,
    "charactersIgnored_lastRun": 0,
    "deltaMinutes": 0
  },
  "vent": {
    "messageId": "67b1414112cdd8e6110bc4cd",
    "time": 1739669825872,
    "messagesAnalyzed_Total": 12388,
    "messagesAnalyzed_lastRun": 0,
    "charactersFound_Total": 8,
    "charactersFound_lastRun": 0,
    "charactersIgnored_Total": 0,
    "charactersIgnored_lastRun": 0,
    "deltaMinutes": 0
  },
  "share": {
    "messageId": "67b1522212cdd8e6110be584",
    "time": 1739674146344,
    "messagesAnalyzed_Total": 6798,
    "messagesAnalyzed_lastRun": 25,
    "charactersFound_Total": 1274,
    "charactersFound_lastRun": 4,
    "charactersIgnored_Total": 7,
    "charactersIgnored_lastRun": 0,
    "deltaMinutes": 109
  }
}