{
  "chat": {
    "messageId": "67b2105912cdd8e6110cc09d",
    "time": 1739722841108,
    "messagesAnalyzed_Total": 109790,
    "messagesAnalyzed_lastRun": 881,
    "charactersFound_Total": 109,
    "charactersFound_lastRun": 0,
    "charactersIgnored_Total": 1,
    "charactersIgnored_lastRun": 0,
    "deltaMinutes": 125
  },
  "chill": {
    "messageId": "67b1dc7b12cdd8e6110c8f15",
    "time": 1739709563586,
    "messagesAnalyzed_Total": 5103,
    "messagesAnalyzed_lastRun": 0,
    "charactersFound_Total": 68,
    "charactersFound_lastRun": 0,
    "charactersIgnored_Total": 0,
    "charactersIgnored_lastRun": 0,
    "deltaMinutes": 0
  },
  "rp": {
    "messageId": "67b1f86e12cdd8e6110ca603",
    "time": 1739716718384,
    "messagesAnalyzed_Total": 19363,
    "messagesAnalyzed_lastRun": 1,
    "charactersFound_Total": 2,
    "charactersFound_lastRun": 0,
    "charactersIgnored_Total": 0,
    "charactersIgnored_lastRun": 0,
    "deltaMinutes": 146
  },
  "spam": {
    "messageId": "67b1988812cdd8e6110c5da8",
    "time": 1739692168440,
    "messagesAnalyzed_Total": 6247,
    "messagesAnalyzed_lastRun": 0,
    "charactersFound_Total": 221,
    "charactersFound_lastRun": 0,
    "charactersIgnored_Total": 0,
    "charactersIgnored_lastRun": 0,
    "deltaMinutes": 0
  },
  "vent": {
    "messageId": "67b2062512cdd8e6110cb58e",
    "time": 1739720229580,
    "messagesAnalyzed_Total": 12397,
    "messagesAnalyzed_lastRun": 1,
    "charactersFound_Total": 8,
    "charactersFound_lastRun": 0,
    "charactersIgnored_Total": 0,
    "charactersIgnored_lastRun": 0,
    "deltaMinutes": 256
  },
  "share": {
    "messageId": "67b1ca1b12cdd8e6110c849b",
    "time": 1739704859306,
    "messagesAnalyzed_Total": 6802,
    "messagesAnalyzed_lastRun": 0,
    "charactersFound_Total": 1274,
    "charactersFound_lastRun": 0,
    "charactersIgnored_Total": 7,
    "charactersIgnored_lastRun": 0,
    "deltaMinutes": 0
  }
}