{
  "chat": {
    "messageId": "68faebf94576572d81bd67b0",
    "time": 1761274873281,
    "messagesAnalyzed_Total": 2183245,
    "messagesAnalyzed_lastRun": 936,
    "charactersFound_Total": 5613,
    "charactersFound_lastRun": 0,
    "charactersIgnored_Total": 2,
    "charactersIgnored_lastRun": 0,
    "duplicatedCharacterLink_Total": 0,
    "duplicatedCharacterLink_lastRun": 0,
    "duplicatedCharacterHash_Total": 0,
    "duplicatedCharacterHash_lastRun": 0,
    "deltaMinutes": 83
  },
  "chill": {
    "messageId": "68fad6a54576572d81bd213a",
    "time": 1761269413471,
    "messagesAnalyzed_Total": 76688,
    "messagesAnalyzed_lastRun": 0,
    "charactersFound_Total": 121,
    "charactersFound_lastRun": 0,
    "charactersIgnored_Total": 0,
    "charactersIgnored_lastRun": 0,
    "duplicatedCharacterLink_Total": 0,
    "duplicatedCharacterLink_lastRun": 0,
    "duplicatedCharacterHash_Total": 0,
    "duplicatedCharacterHash_lastRun": 0,
    "deltaMinutes": 218
  },
  "rp": {
    "messageId": "68fad8604576572d81bd26ee",
    "time": 1761269856401,
    "messagesAnalyzed_Total": 486341,
    "messagesAnalyzed_lastRun": 0,
    "charactersFound_Total": 61,
    "charactersFound_lastRun": 0,
    "charactersIgnored_Total": 0,
    "charactersIgnored_lastRun": 0,
    "duplicatedCharacterLink_Total": 0,
    "duplicatedCharacterLink_lastRun": 0,
    "duplicatedCharacterHash_Total": 0,
    "duplicatedCharacterHash_lastRun": 0,
    "deltaMinutes": 200
  },
  "spam": {
    "messageId": "68fa38244576572d81badc73",
    "time": 1761228836415,
    "messagesAnalyzed_Total": 22482,
    "messagesAnalyzed_lastRun": 0,
    "charactersFound_Total": 782,
    "charactersFound_lastRun": 0,
    "charactersIgnored_Total": 0,
    "charactersIgnored_lastRun": 0,
    "duplicatedCharacterLink_Total": 0,
    "duplicatedCharacterLink_lastRun": 0,
    "duplicatedCharacterHash_Total": 0,
    "duplicatedCharacterHash_lastRun": 0,
    "deltaMinutes": 0
  },
  "vent": {
    "messageId": "68fad81f4576572d81bd260f",
    "time": 1761269791907,
    "messagesAnalyzed_Total": 72569,
    "messagesAnalyzed_lastRun": 0,
    "charactersFound_Total": 20,
    "charactersFound_lastRun": 0,
    "charactersIgnored_Total": 0,
    "charactersIgnored_lastRun": 0,
    "duplicatedCharacterLink_Total": 0,
    "duplicatedCharacterLink_lastRun": 0,
    "duplicatedCharacterHash_Total": 0,
    "duplicatedCharacterHash_lastRun": 0,
    "deltaMinutes": 199
  },
  "share": {
    "messageId": "68fad5ea4576572d81bd1edc",
    "time": 1761269226076,
    "messagesAnalyzed_Total": 22435,
    "messagesAnalyzed_lastRun": 0,
    "charactersFound_Total": 3561,
    "charactersFound_lastRun": 0,
    "charactersIgnored_Total": 32,
    "charactersIgnored_lastRun": 0,
    "duplicatedCharacterLink_Total": 0,
    "duplicatedCharacterLink_lastRun": 0,
    "duplicatedCharacterHash_Total": 0,
    "duplicatedCharacterHash_lastRun": 0,
    "deltaMinutes": 284
  },
  "botshare": {
    "messageId": "68fa09eb4576572d81ba637f",
    "time": 1761217003345,
    "messagesAnalyzed_Total": 2132,
    "messagesAnalyzed_lastRun": 0,
    "charactersFound_Total": 515,
    "charactersFound_lastRun": 0,
    "charactersIgnored_Total": 0,
    "charactersIgnored_lastRun": 0,
    "duplicatedCharacterLink_Total": 0,
    "duplicatedCharacterLink_lastRun": 0,
    "duplicatedCharacterHash_Total": 0,
    "duplicatedCharacterHash_lastRun": 0,
    "deltaMinutes": 0
  },
  "makeabot": {
    "messageId": "68ec6ddf5e669fdb36f919e6",
    "time": 1760325087780,
    "messagesAnalyzed_Total": 131,
    "messagesAnalyzed_lastRun": 0,
    "charactersFound_Total": 18,
    "charactersFound_lastRun": 0,
    "charactersIgnored_Total": 0,
    "charactersIgnored_lastRun": 0,
    "duplicatedCharacterLink_Total": 0,
    "duplicatedCharacterLink_lastRun": 0,
    "duplicatedCharacterHash_Total": 0,
    "duplicatedCharacterHash_lastRun": 0,
    "deltaMinutes": 0
  },
  "nsfw": {
    "messageId": "68fad4e44576572d81bd1bb1",
    "time": 1761268964550,
    "messagesAnalyzed_Total": 8771,
    "messagesAnalyzed_lastRun": 0,
    "charactersFound_Total": 842,
    "charactersFound_lastRun": 0,
    "charactersIgnored_Total": 1,
    "charactersIgnored_lastRun": 0,
    "duplicatedCharacterLink_Total": 0,
    "duplicatedCharacterLink_lastRun": 0,
    "duplicatedCharacterHash_Total": 0,
    "duplicatedCharacterHash_lastRun": 0,
    "deltaMinutes": 284
  },
  "channel-hub": {
    "messageId": "68f862d14576572d81b5a3b8",
    "time": 1761108689043,
    "messagesAnalyzed_Total": 1137,
    "messagesAnalyzed_lastRun": 0,
    "charactersFound_Total": 10,
    "charactersFound_lastRun": 0,
    "charactersIgnored_Total": 0,
    "charactersIgnored_lastRun": 0,
    "duplicatedCharacterLink_Total": 0,
    "duplicatedCharacterLink_lastRun": 0,
    "duplicatedCharacterHash_Total": 0,
    "duplicatedCharacterHash_lastRun": 0,
    "deltaMinutes": 0
  }
}