{
  "chat": {
    "messageId": "69312bc3c8bc67b4fbf11400",
    "time": 1764830147898,
    "messagesAnalyzed_Total": 2527425,
    "messagesAnalyzed_lastRun": 697,
    "charactersFound_Total": 5812,
    "charactersFound_lastRun": 2,
    "charactersIgnored_Total": 2,
    "charactersIgnored_lastRun": 0,
    "duplicatedCharacterLink_Total": 0,
    "duplicatedCharacterLink_lastRun": 0,
    "duplicatedCharacterHash_Total": 0,
    "duplicatedCharacterHash_lastRun": 0,
    "deltaMinutes": 123
  },
  "chill": {
    "messageId": "69310476c8bc67b4fbf095a7",
    "time": 1764820086738,
    "messagesAnalyzed_Total": 83347,
    "messagesAnalyzed_lastRun": 0,
    "charactersFound_Total": 158,
    "charactersFound_lastRun": 0,
    "charactersIgnored_Total": 0,
    "charactersIgnored_lastRun": 0,
    "duplicatedCharacterLink_Total": 0,
    "duplicatedCharacterLink_lastRun": 0,
    "duplicatedCharacterHash_Total": 0,
    "duplicatedCharacterHash_lastRun": 0,
    "deltaMinutes": 102
  },
  "rp": {
    "messageId": "69310ef7c8bc67b4fbf0b9eb",
    "time": 1764822775439,
    "messagesAnalyzed_Total": 535753,
    "messagesAnalyzed_lastRun": 0,
    "charactersFound_Total": 64,
    "charactersFound_lastRun": 0,
    "charactersIgnored_Total": 0,
    "charactersIgnored_lastRun": 0,
    "duplicatedCharacterLink_Total": 0,
    "duplicatedCharacterLink_lastRun": 0,
    "duplicatedCharacterHash_Total": 0,
    "duplicatedCharacterHash_lastRun": 0,
    "deltaMinutes": 71
  },
  "spam": {
    "messageId": "6930eba3c8bc67b4fbf037c6",
    "time": 1764813731529,
    "messagesAnalyzed_Total": 22933,
    "messagesAnalyzed_lastRun": 0,
    "charactersFound_Total": 815,
    "charactersFound_lastRun": 0,
    "charactersIgnored_Total": 0,
    "charactersIgnored_lastRun": 0,
    "duplicatedCharacterLink_Total": 0,
    "duplicatedCharacterLink_lastRun": 0,
    "duplicatedCharacterHash_Total": 0,
    "duplicatedCharacterHash_lastRun": 0,
    "deltaMinutes": 0
  },
  "vent": {
    "messageId": "69310ef2c8bc67b4fbf0b9d7",
    "time": 1764822770169,
    "messagesAnalyzed_Total": 92471,
    "messagesAnalyzed_lastRun": 0,
    "charactersFound_Total": 26,
    "charactersFound_lastRun": 0,
    "charactersIgnored_Total": 0,
    "charactersIgnored_lastRun": 0,
    "duplicatedCharacterLink_Total": 0,
    "duplicatedCharacterLink_lastRun": 0,
    "duplicatedCharacterHash_Total": 0,
    "duplicatedCharacterHash_lastRun": 0,
    "deltaMinutes": 105
  },
  "share": {
    "messageId": "69310d05c8bc67b4fbf0b3f3",
    "time": 1764822277448,
    "messagesAnalyzed_Total": 28655,
    "messagesAnalyzed_lastRun": 0,
    "charactersFound_Total": 5944,
    "charactersFound_lastRun": 0,
    "charactersIgnored_Total": 45,
    "charactersIgnored_lastRun": 0,
    "duplicatedCharacterLink_Total": 0,
    "duplicatedCharacterLink_lastRun": 0,
    "duplicatedCharacterHash_Total": 0,
    "duplicatedCharacterHash_lastRun": 0,
    "deltaMinutes": 126
  },
  "botshare": {
    "messageId": "692f4f092bb334db0fb92ccd",
    "time": 1764708105454,
    "messagesAnalyzed_Total": 2511,
    "messagesAnalyzed_lastRun": 0,
    "charactersFound_Total": 707,
    "charactersFound_lastRun": 0,
    "charactersIgnored_Total": 0,
    "charactersIgnored_lastRun": 0,
    "duplicatedCharacterLink_Total": 0,
    "duplicatedCharacterLink_lastRun": 0,
    "duplicatedCharacterHash_Total": 0,
    "duplicatedCharacterHash_lastRun": 0,
    "deltaMinutes": 0
  },
  "makeabot": {
    "messageId": "68ec6ddf5e669fdb36f919e6",
    "time": 1760325087780,
    "messagesAnalyzed_Total": 170,
    "messagesAnalyzed_lastRun": 0,
    "charactersFound_Total": 27,
    "charactersFound_lastRun": 0,
    "charactersIgnored_Total": 0,
    "charactersIgnored_lastRun": 0,
    "duplicatedCharacterLink_Total": 0,
    "duplicatedCharacterLink_lastRun": 0,
    "duplicatedCharacterHash_Total": 0,
    "duplicatedCharacterHash_lastRun": 0,
    "deltaMinutes": 0
  },
  "nsfw": {
    "messageId": "69302c072cbe107ebab87109",
    "time": 1764764679788,
    "messagesAnalyzed_Total": 12963,
    "messagesAnalyzed_lastRun": 0,
    "charactersFound_Total": 1232,
    "charactersFound_lastRun": 0,
    "charactersIgnored_Total": 2,
    "charactersIgnored_lastRun": 0,
    "duplicatedCharacterLink_Total": 0,
    "duplicatedCharacterLink_lastRun": 0,
    "duplicatedCharacterHash_Total": 0,
    "duplicatedCharacterHash_lastRun": 0,
    "deltaMinutes": 0
  },
  "channel-hub": {
    "messageId": "692f48162bb334db0fb90e57",
    "time": 1764706326619,
    "messagesAnalyzed_Total": 1730,
    "messagesAnalyzed_lastRun": 0,
    "charactersFound_Total": 19,
    "charactersFound_lastRun": 0,
    "charactersIgnored_Total": 0,
    "charactersIgnored_lastRun": 0,
    "duplicatedCharacterLink_Total": 0,
    "duplicatedCharacterLink_lastRun": 0,
    "duplicatedCharacterHash_Total": 0,
    "duplicatedCharacterHash_lastRun": 0,
    "deltaMinutes": 0
  }
}