{
  "folderName": "ai-character-chat+share",
  "message": "https://perchance.org/ai-character-chat?data=Narrator_(the_tribe)_Russian~0b797df5f799bc192a55f1bde7b4df29.gz How's this one? ",
  "messageId": "682259b6ca830f56775c92b4",
  "publicId": "62ddfb69c5bd49b4e9e1",
  "selfDeclaredHistorialPublicIds": [],
  "time": 1747081654383,
  "userNickname": "DTD",
  "userAvatarUrl": "https://user-uploads.perchance.org/file/25f741c08560b033b624db93072768a2.jpg",
  "username": "darrenuk0",
  "replyingTo": "6821cf2aca830f56775b845e"
}