[
  {
    "folderName": "Maria by 768e86057eaf2a89710f",
    "characterName": "Maria",
    "characterName_Sanitized": "Maria",
    "fileId": "717f8834e7c5bee949e2418841ec8590.gz",
    "link": "https://perchance.org/ai-character-chat?data=Maria~717f8834e7c5bee949e2418841ec8590.gz",
    "shareLinkFileHash": "c5c37021cd5a875ca3b60f359cc839cc442581354288e9b5050403f22796fa72",
    "authorName": "768e86057eaf2a89710f",
    "authorId": "768e86057eaf2a89710f"
  },
  {
    "folderName": "Maria by 768e86057eaf2a89710f",
    "characterName": "Maria",
    "characterName_Sanitized": "Maria",
    "fileId": "734baabf770a61bf9f8442df5d05acbe.gz",
    "link": "https://perchance.org/ai-character-chat?data=Maria~734baabf770a61bf9f8442df5d05acbe.gz",
    "shareLinkFileHash": "e75b069d12b99c1062fa8eb6c7a3f36917a453ca20887cdeaf1a472a349ff270",
    "authorName": "768e86057eaf2a89710f",
    "authorId": "768e86057eaf2a89710f"
  },
  {
    "folderName": "Maria by 768e86057eaf2a89710f",
    "characterName": "Maria",
    "characterName_Sanitized": "Maria",
    "fileId": "c1b6eb177df4ef403d36afb0cd1cfa6f.gz",
    "link": "https://perchance.org/ai-character-chat?data=Maria~c1b6eb177df4ef403d36afb0cd1cfa6f.gz",
    "shareLinkFileHash": "28868e4d3791f42797970289c86cf2aadc0f54313e9722640dc0591ced594d22",
    "authorName": "768e86057eaf2a89710f",
    "authorId": "768e86057eaf2a89710f"
  },
  {
    "folderName": "Maria by 768e86057eaf2a89710f",
    "characterName": "Maria",
    "characterName_Sanitized": "Maria",
    "fileId": "cf848baac2af753649b83b9c9febffe5.gz",
    "link": "https://perchance.org/ai-character-chat?data=Maria~cf848baac2af753649b83b9c9febffe5.gz",
    "shareLinkFileHash": "bd2a46960b4961aa12a4d865d1c172baff9e07868e63a5457a1abd642958c634",
    "authorName": "768e86057eaf2a89710f",
    "authorId": "768e86057eaf2a89710f"
  },
  {
    "folderName": "Maria by 768e86057eaf2a89710f",
    "characterName": "Maria",
    "characterName_Sanitized": "Maria",
    "fileId": "e6f81f0bab02da3dffab6498a8f3cee3.gz",
    "link": "https://perchance.org/ai-character-chat?data=Maria~e6f81f0bab02da3dffab6498a8f3cee3.gz",
    "shareLinkFileHash": "c869dfcbbbad0cfb6b30fd2311225516d5041b0ffab93adeae8c2a591facae25",
    "authorName": "768e86057eaf2a89710f",
    "authorId": "768e86057eaf2a89710f"
  },
  {
    "folderName": "Maria by 768e86057eaf2a89710f",
    "characterName": "Maria",
    "characterName_Sanitized": "Maria",
    "fileId": "852d00ee27baf5d0b2b981380245f424.gz",
    "link": "https://perchance.org/ai-character-chat?data=Maria~852d00ee27baf5d0b2b981380245f424.gz",
    "shareLinkFileHash": "61489cf29841e2fc177a40aa48f95678e7fbafb57e88fd2716873283c1bfc11d",
    "authorName": "768e86057eaf2a89710f",
    "authorId": "768e86057eaf2a89710f"
  }
]