{
  "folderName": "ai-character-chat+chat",
  "message": "https://perchance.org/ai-character-chat?data=Style_2_Character_Generator~41d3ffd5351236eced71845a77adf575.gz",
  "messageId": "67af959b12cdd8e611094b13",
  "publicId": "f6a2e122beb96c8e7ce1",
  "selfDeclaredHistorialPublicIds": [],
  "time": 1739560347566,
  "userNickname": "Bus- Mother of Matt and Ph03n1x",
  "userAvatarUrl": "https://user-uploads.perchance.org/file/9cf70cc118582b390a07b6e42264e6e2.jpg",
  "username": "bus01",
  "replyingTo": "67af959312cdd8e611094b06"
}