{
  "folderName": "ai-character-chat+share",
  "message": "Femboy plant man in post goblin Britain = https://perchance.org/ai-character-chat?data=Lysander_Finch~2ec7cb6a7d8bf71b6de956e36c4b15ab.gz",
  "messageId": "69162d0d627d9d30c2efbcb9",
  "publicId": "129fc13a23bd2ada2ee7",
  "selfDeclaredHistorialPublicIds": [
    "107e044d57a1d4658fd3",
    "70288f652d0341e38846",
    "6d72cc46f1839419a43c",
    "f367411f751f97e752a0",
    "e975e6f900e749cf0703"
  ],
  "time": 1763061005053,
  "userNickname": "The_NNN",
  "userAvatarUrl": null
}