{
  "folderName": "ai-character-chat+chat",
  "message": "https://perchance.org/ai-character-chat?data=Serial_Designation_J~98f425c5aa5a6ae07a019362215a995d.gz вот кароче персонаж, поясни поч лор не работает пж",
  "messageId": "67defab0953da9abc1f2c76a",
  "publicId": "9de4075f4892ddc4095c",
  "selfDeclaredHistorialPublicIds": [],
  "time": 1742666416237,
  "userNickname": "DoKtOr",
  "userAvatarUrl": "https://user-uploads.perchance.org/file/3c5bc8bcc7dc5b1e703caf65c4a8baaa.jpeg",
  "replyingTo": "67defa72953da9abc1f2c726"
}