{
  "folderName": "ai-character-chat+chat",
  "message": "https://perchance.org/ai-character-chat?data=Scylla~9192b3a9fa48b6651502700d1929124b.gz",
  "messageId": "67f02bcf256c9e5b34cd009c",
  "publicId": "542f4b5d0628439913c4",
  "selfDeclaredHistorialPublicIds": [],
  "time": 1743793103908,
  "userNickname": "Abby. She/her. Straight. Besties: posidon2, Eve.",
  "userAvatarUrl": "https://user-uploads.perchance.org/file/752655dc27381fa07d8aa541b5b6fcc6.jpg",
  "username": "circe786",
  "replyingTo": "67f02ba2256c9e5b34cd005a"
}