[
  {
    "folderName": "komiyandere_variant by sapcattree12",
    "characterName": "komi(yandere_variant)",
    "characterName_Sanitized": "komiyandere_variant",
    "fileId": "7c2db4aec43406a4afe76a71372a3d73.gz",
    "link": "https://perchance.org/ai-character-chat?data=komi(yandere_variant)~7c2db4aec43406a4afe76a71372a3d73.gz",
    "shareLinkFileHash": "c4a12cc1cb5ce2aa24ea032a1d815cb71d61dd8e89c43428c406726633e544cb",
    "authorName": "sapcattree12",
    "authorId": "bafe8287949558e314d3"
  }
]