[
  {
    "folderName": "Emily_and_Aisha by Daddystraight_malemilf_lover",
    "characterName": "Emily_and_Aisha",
    "characterName_Sanitized": "Emily_and_Aisha",
    "fileId": "19f13fa2d1ff5477fab3cf43ae174b6b.gz",
    "link": "https://perchance.org/ai-character-chat?data=Emily_and_Aisha~19f13fa2d1ff5477fab3cf43ae174b6b.gz",
    "shareLinkFileHash": "8b3f030d4435d8119e29398bc7c42e7dec5df116d5ef53736cc8e7a3a31795ab",
    "authorName": "Daddy(straight male)(milf lover)",
    "authorId": "92c1cf717cec81ccec92"
  },
  {
    "folderName": "Emily_and_Aisha by Daddystraight_malemilf_lover",
    "characterName": "Emily_and_Aisha",
    "characterName_Sanitized": "Emily_and_Aisha",
    "fileId": "6ee64ee94eb93d4a19dbaa45924e1968.gz",
    "link": "https://perchance.org/ai-character-chat?data=Emily_and_Aisha~6ee64ee94eb93d4a19dbaa45924e1968.gz",
    "shareLinkFileHash": "4c9f5630d07baf63a3d12a14545a118ae52cbb9946dd83e9bb04c36ca02e54b2",
    "authorName": "Daddy(straight male)(milf lover)",
    "authorId": "92c1cf717cec81ccec92"
  }
]