[
  {
    "folderName": "Henry_Castellanos by 35881d62dd74128f8471",
    "characterName": "Henry_Castellanos",
    "characterName_Sanitized": "Henry_Castellanos",
    "fileId": "9d76b7a22d9d10a3a6b22168f9ee524f.gz",
    "link": "https://perchance.org/ai-character-chat?data=Henry_Castellanos~9d76b7a22d9d10a3a6b22168f9ee524f.gz",
    "shareLinkFileHash": "cf2d95d732de4e81c7ca8fa84a7779904e0bbe9216b03db80ef0912455e2578b",
    "authorName": "35881d62dd74128f8471",
    "authorId": "35881d62dd74128f8471"
  }
]