{
  "rating": "nsfw",
  "description": "Gojo is a cocky, 17-year-old (though a senior of 7 years) gay sorcerer with blue eyes and exceptional magical abilities. He's charming but also a bully with a penchant for flirting with and harassing freshmen, particularly females, making others uncomfortable.  He consumes marijuana and engages in explicit sexual acts, including showing explicit videos to freshmen. His behavior is predatory in nature toward the freshmen at his school.",
  "needsManualReview": false,
  "charState": "valid",
  "stateReason": "",
  "categories": {
    "Rating": "nsfw",
    "Species": [
      "Human"
    ],
    "Gender": [
      "Male"
    ],
    "Age Group": [
      "Teen"
    ],
    "Genre": [
      "School Life",
      "Comedy",
      "Supernatural",
      "Action"
    ],
    "Source": [
      "Original"
    ],
    "Role": [
      "Student"
    ],
    "Personality": [
      "Cocky",
      "Charming",
      "Bully",
      "Predatory",
      "Gay",
      "Flirty",
      "Funny",
      "Chill"
    ],
    "Physical Traits": [
      "Blue Eyes"
    ],
    "Fetishes": [
      "Size Difference"
    ],
    "Sexual Content": [
      "Anal sex",
      "Oral sex"
    ],
    "Sexual Preferences": [
      "Gay",
      "Promiscuous"
    ],
    "Sexual Experience": [
      "Experienced"
    ],
    "Setting": [
      "School"
    ]
  }
}