{
  "folderName": "ai-character-chat+chat",
  "message": "(updated this again)\n\nhttps://perchance.org/ai-character-chat?data=Character_generator~1bbbd1ab562bcd3c7f7ad37180a56f54.gz",
  "messageId": "67ae163b12cdd8e61106fbd7",
  "publicId": "f6a2e122beb96c8e7ce1",
  "selfDeclaredHistorialPublicIds": [],
  "time": 1739462203374,
  "userNickname": "Bus- Mother of Matt and Ph03n1x",
  "userAvatarUrl": "https://user-uploads.perchance.org/file/9cf70cc118582b390a07b6e42264e6e2.jpg",
  "username": "bus01",
  "replyingTo": "67ae163512cdd8e61106fbcf"
}