{
  "folderName": "ai-character-chat+share",
  "message": "Rollo Flamme, whatever update this is, I added the info about his younger brother, the Kindly Bell Ringer (too lazy to say it was Disney Animation's variant of Quasimodo) and Rollo's diary: https://perchance.org/ai-character-chat?data=Rollo_Flamme~388395f4e68f37e316b527158443de64.gz\nI went hog wild, this is probably going to be my last update as now I've covered most of the lore not mentioned on the Wiki page.",
  "messageId": "680152f580c839f98ae22c2e",
  "publicId": "1d7acbfdc9288663d609",
  "selfDeclaredHistorialPublicIds": [],
  "time": 1744917237601,
  "userNickname": "Yuliana",
  "userAvatarUrl": "https://user-uploads.perchance.org/file/a889b4a0c06b77d2eca05be11d3a923c.jpg"
}