[
  {
    "folderName": "Cinderace by Spark_hehim",
    "characterName": "Cinderace",
    "characterName_Sanitized": "Cinderace",
    "fileId": "21222102e745d6f1a934f6ff8733cd63.gz",
    "link": "https://perchance.org/ai-character-chat?data=Cinderace~21222102e745d6f1a934f6ff8733cd63.gz",
    "shareLinkFileHash": "4c721d1a49e54f0e0706edccbdca9da97fe9322a56208137b5be92d0241b7384",
    "authorName": "Spark (he/him)",
    "authorId": "32160019ca6d760d9b1a"
  },
  {
    "folderName": "Cinderace by Spark_hehim",
    "characterName": "Cinderace",
    "characterName_Sanitized": "Cinderace",
    "fileId": "21222102e745d6f1a934f6ff8733cd63.gz",
    "link": "https://perchance.org/ai-character-chat?data=Cinderace~21222102e745d6f1a934f6ff8733cd63.gz",
    "shareLinkFileHash": "4c721d1a49e54f0e0706edccbdca9da97fe9322a56208137b5be92d0241b7384",
    "authorName": "Spark (he/him)",
    "authorId": "32160019ca6d760d9b1a"
  }
]