{
  "folderName": "ai-character-chat+share",
  "message": "Literally just the same bot of mine but with proper name and designation: Novel and play\nhttps://perchance.org/ai-character-chat?data=Tinker_Bell~67c31c400e00813f0edab0e3ff404f8c.gz",
  "messageId": "684f51e0dc62d89c3a5b78aa",
  "publicId": "c6110ca7c3a96bd69310",
  "selfDeclaredHistorialPublicIds": [],
  "time": 1750028768979,
  "userNickname": "Juliane",
  "userAvatarUrl": "https://user.uploads.dev/file/02dcc342a56840551202c9b0b8e40d1a.jpg"
}