{
  "folderName": "ai-character-chat+chat",
  "message": "https://perchance.org/ai-character-chat?data=Shark_Sorbet_Cookie~317333be86ff2df6a98395a6b676fd9c.gz https://perchance.org/ai-character-chat?data=Shadow_Milk_Cookie~77ebcadb5aa612e379a7144e2fa4a995.gz https://perchance.org/ai-character-chat?data=Princess_Samantha~64255f28209f294db554aa82178065e1.gz https://perchance.org/ai-character-chat?data=N~91a3d63793039fba910c6567091deca6.gz \n",
  "messageId": "692ab7b61fdb8b0c8634d382",
  "publicId": "35dfd0209c4401fa0fb5",
  "selfDeclaredHistorialPublicIds": [
    "194eaaccf61c1d9d7fa1",
    "e0cb2c8c49d99008f450"
  ],
  "time": 1764407222575,
  "userNickname": "Cookie Lover",
  "userAvatarUrl": "https://user.uploads.dev/file/7c7577c3bc17df2515cbef62daa183ff.jpg",
  "username": "almondcooki3"
}