{
  "folderName": "ai-character-chat+chat",
  "message": "https://perchance.org/ai-character-chat?data=Megavolt_(Elmo_Sputterspark)~4f8d45c52bf5aefe8514c851f510baca.gz",
  "messageId": "69237fe45b394d9ecc290c96",
  "publicId": "c18ec29082c17236be73",
  "selfDeclaredHistorialPublicIds": [],
  "time": 1763934180181,
  "userNickname": "Gwimbly “I’m a fatass”",
  "userAvatarUrl": "https://user.uploads.dev/file/f22876b902ac83310f5f09995744e262.jpg",
  "username": "sirmixalot",
  "replyingTo": "69237faf5b394d9ecc290bb6"
}