{
  "folderName": "ai-character-chat+chat",
  "message": "i made a male one: https://perchance.org/ai-character-chat?data=Niyan~5d3b452bd636c25e60dfcd09214c5208.gz \nAnd im working on another verison of game master but idrk if its gonna be like any diffrent besides the stolen code",
  "messageId": "67f1d5f2256c9e5b34cf58ce",
  "publicId": "f5324bdef59694fe61f8",
  "selfDeclaredHistorialPublicIds": [],
  "time": 1743902194714,
  "userNickname": null,
  "userAvatarUrl": "https://user-uploads.perchance.org/file/41a29cf659578c0d61595d5718a09229.jpg",
  "username": "dotxet",
  "replyingTo": "67f1d580256c9e5b34cf5819"
}